synset/__init__.py
synset/_modidx.py
synset/core.py
synset-0.0.15.dist-info/LICENSE
synset-0.0.15.dist-info/METADATA
synset-0.0.15.dist-info/WHEEL
synset-0.0.15.dist-info/entry_points.txt
synset-0.0.15.dist-info/top_level.txt
synset-0.0.15.dist-info/RECORD
