Metadata-Version: 2.1
Name: synset
Version: 0.0.15
Summary: synset
Home-page: https://github.com/dsm-72/synset
Author: dsm-72
Author-email: sumner.magruder@yale.edu
License: Apache Software License 2.0
Keywords: syn synonyms alias set aliasable canon canonical name things with fuzzy string matching synset nym str fuz fuzstr atyp ispec indoc dynattr
Classifier: Development Status :: 4 - Beta
Classifier: Intended Audience :: Developers
Classifier: Natural Language :: English
Classifier: Programming Language :: Python :: 3.11
Classifier: License :: OSI Approved :: Apache Software License
Requires-Python: >=3.11
License-File: LICENSE
Requires-Dist: atyp
Requires-Dist: regsyn
Requires-Dist: indoc
Requires-Dist: ispec
Requires-Dist: pstr
Requires-Dist: nymstr
Requires-Dist: fuzstr
Requires-Dist: aspec
Provides-Extra: dev
